av/AppVersion.py
appversion-0.0.1.dist-info/LICENSE
appversion-0.0.1.dist-info/METADATA
appversion-0.0.1.dist-info/WHEEL
appversion-0.0.1.dist-info/top_level.txt
appversion-0.0.1.dist-info/RECORD
