Metadata-Version: 2.1
Name: appversion
Version: 0.0.1
Summary: Get app version from playstore, appstore
Home-page: https://github.com/tinyjin/appversion
Author: tinyjin
Author-email: baram991103@gmail.com
License: MIT
Keywords: app version playstore appstore
Platform: UNKNOWN
Classifier: Programming Language :: Python :: 3
Classifier: License :: OSI Approved :: MIT License
Classifier: Operating System :: OS Independent
Requires-Dist: beautifulsoup4
Requires-Dist: requests
